{"platforms":{"platform":[{"name":"Nintendo 3DS (carte)","id":18,"device":"CTR","category":8},{"name":"Nintendo 3DS (téléchargement)","id":19,"device":"CTR","category":8},{"name":"Nintendo DSiWare","id":20,"device":"CTR","category":9},{"name":"Game Boy","id":21,"device":"CTR","category":10},{"name":"Game Boy Color","id":22,"device":"CTR","category":10},{"name":"NES","id":24,"device":"CTR","category":10},{"name":"Game Gear","id":25,"device":"CTR","category":10},{"name":"Vidéo téléchargeable","id":43,"device":"CTR","category":8},{"name":"Données de mise à jour","id":63,"device":"CTR","category":8},{"name":"Nintendo 3DS (carte/téléch.)","id":103,"device":"CTR","category":8},{"name":"New 3DS (téléchargement)","id":1001,"device":"CTR","category":8},{"name":"New 3DS (carte/téléch.)","id":1002,"device":"CTR","category":8},{"name":"Super Nintendo","id":1004,"device":"CTR","category":10}],"length":13}}